watchmen_pipeline_surface/__init__.py
watchmen_pipeline_surface/connectors/__init__.py
watchmen_pipeline_surface/connectors/handler.py
watchmen_pipeline_surface/connectors/kafka.py
watchmen_pipeline_surface/connectors/rabbitmq.py
watchmen_pipeline_surface/data/__init__.py
watchmen_pipeline_surface/data/monitor_log_router.py
watchmen_pipeline_surface/data/pipeline_trigger_router.py
watchmen_pipeline_surface/data/topic_snapshot_adhoc_router.py
watchmen_pipeline_surface/data/topic_trigger_router.py
watchmen_pipeline_surface/main.py
watchmen_pipeline_surface/settings.py
watchmen_pipeline_surface/surface.py
watchmen_pipeline_surface-18.0.1.dist-info/METADATA
watchmen_pipeline_surface-18.0.1.dist-info/WHEEL
watchmen_pipeline_surface-18.0.1.dist-info/licenses/LICENSE
watchmen_pipeline_surface-18.0.1.dist-info/RECORD
