Metadata-Version: 2.4
Name: watchmen-pipeline-surface
Version: 18.0.1
Summary: 
License: MIT
License-File: LICENSE
Author: botlikes
Author-email: 75356972+botlikes456@users.noreply.github.com
Requires-Python: >=3.12,<3.13
Classifier: License :: OSI Approved :: MIT License
Classifier: Programming Language :: Python :: 3
Classifier: Programming Language :: Python :: 3.12
Provides-Extra: collector
Provides-Extra: es-ext-writer
Provides-Extra: kafka
Provides-Extra: mongodb
Provides-Extra: mssql
Provides-Extra: mysql
Provides-Extra: oracle
Provides-Extra: postgresql
Provides-Extra: rabbitmq
Provides-Extra: standard-ext-writer
Requires-Dist: aio-pika (>=9.4.2,<10.0.0) ; extra == "rabbitmq"
Requires-Dist: aiokafka (>=0.11.0,<0.12.0) ; extra == "kafka"
Requires-Dist: kafka-python (>=2.0.2,<3.0.0) ; extra == "kafka"
Requires-Dist: requests (>=2.32.3,<3.0.0) ; extra == "standard-ext-writer"
Requires-Dist: watchmen-pipeline-kernel (==18.0.1)
Requires-Dist: watchmen-rest (==18.0.1)
Requires-Dist: watchmen-storage-mongodb (==18.0.1) ; extra == "mongodb"
Requires-Dist: watchmen-storage-mssql (==18.0.1) ; extra == "mssql"
Requires-Dist: watchmen-storage-mysql (==18.0.1) ; extra == "mysql"
Requires-Dist: watchmen-storage-oracle (==18.0.1) ; extra == "oracle"
Requires-Dist: watchmen-storage-postgresql (==18.0.1) ; extra == "postgresql"
